README.md
setup.cfg
setup.py
nepal_company_registrar.egg-info/PKG-INFO
nepal_company_registrar.egg-info/SOURCES.txt
nepal_company_registrar.egg-info/dependency_links.txt
nepal_company_registrar.egg-info/requires.txt
nepal_company_registrar.egg-info/top_level.txt
nepali_company_registrar/__init__.py
nepali_company_registrar/conf.py
nepali_company_registrar/datasets.py
nepali_company_registrar/exceptions.py
nepali_company_registrar/models.py
nepali_company_registrar/nepal_company_registrar.py
nepali_company_registrar/test.py