Metadata-Version: 2.1
Name: nepal-company-registrar
Version: 0.0.3
Summary: A package for nepal company registrar
Home-page: https://github.com/sbishnu019/nepal-company-registrar.git
Author: Bishnu Sharma
Author-email: sbishnu019@gmail.com
License: UNKNOWN
Download-URL: https://github.com/sbishnu019/nepal-company-registrar/archive/v0.0.3.tar.gz
Platform: UNKNOWN
Classifier: Programming Language :: Python :: 3
Classifier: License :: OSI Approved :: MIT License
Classifier: Operating System :: OS Independent
Requires-Python: >=3.6
